{
    "b": [
        "be",
        "become",
        "bring",
        "build",
        "begin",
        "believe",
        "base",
        "buy",
        "break",
        "bear"
    ],
    "h": [
        "have",
        "help",
        "hold",
        "happen",
        "hear",
        "hope",
        "hit"
    ],
    "d": [
        "do",
        "develop",
        "decide",
        "design",
        "drive",
        "describe",
        "discuss",
        "deliver",
        "determine",
        "depend",
        "die",
        "draw",
        "discover",
        "define"
    ],
    "m": [
        "make",
        "mean",
        "move",
        "meet",
        "manage",
        "mention",
        "maintain",
        "miss"
    ],
    "g": [
        "get",
        "go",
        "give",
        "grow"
    ],
    "u": [
        "use",
        "understand"
    ],
    "s": [
        "say",
        "see",
        "start",
        "show",
        "seem",
        "set",
        "support",
        "share",
        "spend",
        "send",
        "serve",
        "sell",
        "speak",
        "stop",
        "save",
        "stay",
        "suggest",
        "seek",
        "stand",
        "sit",
        "sign"
    ],
    "t": [
        "take",
        "think",
        "try",
        "tell",
        "turn",
        "talk",
        "thank",
        "teach"
    ],
    "k": [
        "know",
        "keep",
        "kill"
    ],
    "f": [
        "find",
        "feel",
        "follow",
        "focus",
        "fall",
        "face",
        "feature",
        "fill",
        "fail"
    ],
    "w": [
        "work",
        "want",
        "write",
        "watch",
        "win",
        "wait",
        "walk",
        "wish"
    ],
    "c": [
        "come",
        "create",
        "call",
        "change",
        "continue",
        "consider",
        "choose",
        "cover",
        "cause",
        "check",
        "contain",
        "carry",
        "complete",
        "cut",
        "connect",
        "compare",
        "contact",
        "collect"
    ],
    "n": [
        "need",
        "note"
    ],
    "i": [
        "include",
        "increase",
        "involve",
        "improve",
        "identify",
        "introduce"
    ],
    "p": [
        "provide",
        "put",
        "pay",
        "play",
        "post",
        "produce",
        "pass",
        "publish",
        "present",
        "please",
        "plan",
        "protect",
        "place",
        "prepare",
        "perform",
        "pick",
        "promote",
        "prevent",
        "participate"
    ],
    "l": [
        "look",
        "learn",
        "leave",
        "like",
        "live",
        "let",
        "love",
        "lead",
        "lose"
    ],
    "r": [
        "read",
        "run",
        "require",
        "receive",
        "remain",
        "remember",
        "reduce",
        "reach",
        "report",
        "raise",
        "return",
        "relate",
        "represent",
        "remove",
        "release",
        "recommend",
        "realize",
        "recognize"
    ],
    "a": [
        "ask",
        "add",
        "allow",
        "apply",
        "appear",
        "accord",
        "agree",
        "achieve",
        "address",
        "accept",
        "affect",
        "avoid",
        "announce",
        "attend"
    ],
    "o": [
        "offer",
        "open",
        "operate",
        "occur"
    ],
    "e": [
        "enjoy",
        "expect",
        "ensure",
        "eat",
        "end",
        "explain",
        "enter",
        "establish",
        "encourage",
        "exist",
        "enable",
        "engage",
        "experience",
        "explore"
    ],
    "j": [
        "join"
    ],
    "v": [
        "visit"
    ]
}